PString.py
pstring-1.0.2.dist-info/LICENSE
pstring-1.0.2.dist-info/METADATA
pstring-1.0.2.dist-info/WHEEL
pstring-1.0.2.dist-info/top_level.txt
pstring-1.0.2.dist-info/RECORD
