Metadata-Version: 2.1
Name: pstring
Version: 1.0.2
Summary: PString is a str class that recognizes IPA symbols.
Author-email: Caio Rocha <caiocedrola@ice.ufjf.br>
License: MIT License
Keywords: ipa,phoneme,phonetics
Classifier: License :: OSI Approved :: MIT License
Classifier: Programming Language :: Python
Classifier: Programming Language :: Python :: 3
Requires-Python: >=3.7
License-File: LICENSE
